README.md
setup.py
keycloak_wrapper/__init__.py
keycloak_wrapper/keycloak_patterns.py
keycloak_wrapper/wrapper.py
keycloak_wrapper.egg-info/PKG-INFO
keycloak_wrapper.egg-info/SOURCES.txt
keycloak_wrapper.egg-info/dependency_links.txt
keycloak_wrapper.egg-info/not-zip-safe
keycloak_wrapper.egg-info/requires.txt
keycloak_wrapper.egg-info/top_level.txt