Metadata-Version: 1.0
Name: keycloak-wrapper
Version: 0.2
Summary: A python wrapper for keycloak
Home-page: https://github.com/kapsali29/keycloak_wrapper
Author: Panagiotis Kapsalis
Author-email: kapsali29@gmail.com
License: MIT
Platform: UNKNOWN
